dash_connectivity_viewer/__init__.py
dash_connectivity_viewer/cell_type_connectivity/__init__.py
dash_connectivity_viewer/cell_type_connectivity/callbacks.py
dash_connectivity_viewer/cell_type_connectivity/config.py
dash_connectivity_viewer/cell_type_connectivity/cortex_panels.py
dash_connectivity_viewer/cell_type_connectivity/cortex_plots.py
dash_connectivity_viewer/cell_type_connectivity/external_stylesheets.py
dash_connectivity_viewer/cell_type_connectivity/layout.py
dash_connectivity_viewer/cell_type_connectivity/neuron_data_cortex.py
dash_connectivity_viewer/cell_type_table/__init__.py
dash_connectivity_viewer/cell_type_table/callbacks.py
dash_connectivity_viewer/cell_type_table/config.py
dash_connectivity_viewer/cell_type_table/ct_utils.py
dash_connectivity_viewer/cell_type_table/layout.py
dash_connectivity_viewer/common/__init__.py
dash_connectivity_viewer/common/config.py
dash_connectivity_viewer/common/dash_url_helper.py
dash_connectivity_viewer/common/dataframe_utilities.py
dash_connectivity_viewer/common/external_stylesheets.py
dash_connectivity_viewer/common/link_utilities.py
dash_connectivity_viewer/common/lookup_utilities.py
dash_connectivity_viewer/common/neuron_data_base.py
dash_connectivity_viewer/common/schema_utils.py
dash_connectivity_viewer/common/table_lookup.py
dash_connectivity_viewer/common/transform_utils.py
dash_connectivity_viewer/common/data/height_bounds_v1.npy
dash_connectivity_viewer/common/data/layer_bounds_v1.npy
dash_connectivity_viewer/connectivity_table/__init__.py
dash_connectivity_viewer/connectivity_table/callbacks.py
dash_connectivity_viewer/connectivity_table/config.py
dash_connectivity_viewer/connectivity_table/layout.py
dash_connectivity_viewer-2.2.7.dist-info/METADATA
dash_connectivity_viewer-2.2.7.dist-info/WHEEL
dash_connectivity_viewer-2.2.7.dist-info/licenses/LICENSE.txt
dash_connectivity_viewer-2.2.7.dist-info/RECORD
