Metadata-Version: 2.4
Name: dash-connectivity-viewer
Version: 2.2.7
Summary: Dash connectivity viewer for CAVE data
Project-URL: Homepage, https://github.com/ceesem/dash-connectivity-viewer
Project-URL: Bug Tracker, https://github.com/ceesem/dash-connectivity-viewer/issues
Author-email: Casey Schneider-Mizell <caseysm@gmail.com>
License: MIT
License-File: LICENSE.txt
Classifier: License :: OSI Approved :: MIT License
Classifier: Operating System :: OS Independent
Classifier: Programming Language :: Python :: 3
Requires-Python: >=3.7
Requires-Dist: cachetools
Requires-Dist: caveclient>=5.20.0
Requires-Dist: dash-bootstrap-components>=1
Requires-Dist: dash>=2
Requires-Dist: dfbridge>=0.0.2
Requires-Dist: flask
Requires-Dist: loguru
Requires-Dist: nglui>=3
Requires-Dist: numpy
Requires-Dist: orjson
Requires-Dist: pandas
Requires-Dist: plotly>=5
Requires-Dist: requests
Requires-Dist: seaborn
Requires-Dist: standard-transform>=1
